{
  "일주": "경오",
  "한자": "庚午",
  "기본이미지": "눈부신 햇살 아래 달리는 기품 있는 백마. 뜨거운 용광로에서 제련되는 단단한 쇠. 투명한 솔직함과 완벽주의로 세상을 당당하게 살아가는 정의로운 스타.",
  "운세": {
    "장생": [
      {
        "v": 1,
        "타입": "심오",
        "제목": "백마의 첫걸음",
        "본문": "오늘,\n눈부신 햇살 아래 새하얀 말 한 마리가 첫걸음을 내딛어요.\n庚은 쇠,\n午는 불.\n당신 안에 잠들어 있던 정의로운 마음이,\n조용히 깨어나는 순간이에요.\n새로운 시작은 투명하고 솔직해요.\n거짓 없이 나아갈 때,\n세상은 당신의 당당함에 길을 열어줄 거예요.\n오늘은 당신의 내면에 있는 원칙과 명예가,\n빛을 발하기 시작하는 날이에요.",
        "액션": "정직하게 시작하세요. 당신의 솔직함과 원칙으로 첫발을 내딛으면, 세상이 당신을 믿고 따를 거예요."
      },
      {
        "v": 2,
        "타입": "심오",
        "제목": "용광로의 불씨",
        "본문": "오늘,\n차가운 쇠가 뜨거운 용광로 안으로 들어가요.\n완벽해지기 위한 긴 여정의 시작이에요.\n당신은 스스로를 제련하는 사람이에요.\n남들이 쉴 때도,\n자신을 갈고닦는 것을 멈추지 않아요.\n이 열정이,\n당신을 세상에서 가장 단단하고 빛나는 존재로 만들 거예요.\n오늘은 당신의 자기 관리와 완벽주의가,\n빛을 발하기 시작하는 날이에요.",
        "액션": "스스로를 단련하세요. 완벽을 향한 당신의 노력이 쌓일 때, 누구도 흉내 낼 수 없는 명검이 될 거예요."
      },
      {
        "v": 3,
        "타입": "심오",
        "제목": "투명한 영혼",
        "본문": "오늘,\n당신의 솔직함이 세상을 밝혀요.\n나체도화,\n옷을 벗은 것처럼 투명한 영혼이에요.\n거짓을 모르고,\n꾸밈이 없어요.\n이 정직함이 사람들의 마음을 움직여요.\n당신이 진심으로 말할 때,\n세상은 귀를 기울이고 신뢰를 보내요.\n오늘은 당신의 솔직함이,\n가장 큰 힘이 되는 날이에요.",
        "액션": "진심을 말하세요. 거짓 없는 당신의 한마디가 누군가의 마음을 열고, 세상을 조금 더 따뜻하게 만들 거예요."
      },
      {
        "v": 4,
        "타입": "심오",
        "제목": "명예로운 출발",
        "본문": "오늘,\n백마는 화려한 무대 위에 서요.\n정관의 기운,\n명예와 원칙이 당신을 빛나게 해요.\n당신은 남들 앞에 설 때,\n가장 큰 에너지를 받는 사람이에요.\n주목받는 것을 즐기고,\n그 기대에 부응하기 위해 더욱 노력해요.\n오늘은 당신의 명예욕과 리더십이,\n세상에 드러나기 시작하는 날이에요.",
        "액션": "무대에 오르세요. 사람들의 시선을 받을 때 당신은 가장 빛나며, 그 명예를 통해 더 큰 성장을 이룰 거예요."
      },
      {
        "v": 5,
        "타입": "심오",
        "제목": "정의의 깃발",
        "본문": "오늘,\n당신은 정의를 향해 달려요.\n불의를 보면 참지 못하는 사람이에요.\n강한 자에게는 강하고,\n약한 자에게는 따뜻해요.\n당신의 직선적인 성격이,\n때로는 오해를 부를 수 있지만,\n그 정의로움이 결국 세상을 바꿔요.\n오늘은 당신의 원칙과 기개가,\n누군가에게 희망이 되는 날이에요.",
        "액션": "옳은 것을 말하세요. 당신의 정의로운 한마디가 누군가를 구하고, 세상을 조금 더 바르게 만들 거예요."
      },
      {
        "v": 6,
        "타입": "중립",
        "제목": "새로운 출발의 설렘",
        "본문": "오늘,\n모든 것이 새롭게 시작돼요.\n뭔가 설레는 일이 생길 것 같아요.\n처음이라 서툴 수 있지만,\n그 서툼이 오히려 당신을 더 매력적으로 만들어요.\n시작은 언제나 조심스럽지만,\n그 안에는 무한한 가능성이 담겨 있어요.\n오늘은 새로운 인연이나 기회가,\n당신 앞에 모습을 드러내는 날이에요.",
        "액션": "새로운 것을 시작해보세요. 낯설더라도 도전하면, 예상치 못한 기쁨과 성장을 얻게 될 거예요."
      },
      {
        "v": 7,
        "타입": "중립",
        "제목": "씨앗을 심는 시간",
        "본문": "오늘,\n당신이 심는 씨앗 하나가,\n미래의 큰 숲이 될 거예요.\n지금 하는 작은 노력이,\n나중에 큰 결실로 돌아와요.\n조급해하지 말고,\n한 걸음씩 천천히 나아가세요.\n뿌리가 깊어질수록,\n나무는 더 단단하게 자라요.\n오늘은 미래를 위해 준비하는,\n소중한 시간이에요.",
        "액션": "차근차근 준비하세요. 지금 쌓는 작은 노력들이 모여, 미래에 당신을 단단하게 지탱해줄 거예요."
      },
      {
        "v": 8,
        "타입": "중립",
        "제목": "작은 희망의 싹",
        "본문": "오늘,\n작지만 분명한 희망이 보여요.\n아직 눈에 띄지 않을 수 있지만,\n당신의 마음속에서 뭔가 싹트고 있어요.\n그것을 소중히 키워가세요.\n매일 조금씩 관심을 주고,\n사랑으로 돌보다 보면,\n어느새 당신의 삶을 채우는 큰 기쁨이 될 거예요.\n오늘은 희망을 품는,\n따뜻한 날이에요.",
        "액션": "희망을 키워가세요. 작은 꿈이라도 포기하지 않고 돌보면, 언젠가 당신의 인생을 바꿀 거예요."
      },
      {
        "v": 9,
        "타입": "중립",
        "제목": "조용한 준비",
        "본문": "오늘,\n당신은 조용히 준비하고 있어요.\n남들 눈에 띄지 않아도 괜찮아요.\n진짜 중요한 것은,\n드러나지 않는 곳에서 쌓이고 있어요.\n완벽한 준비가 끝났을 때,\n세상은 당신을 발견하고 놀랄 거예요.\n오늘은 묵묵히 자신을 갈고닦는,\n귀한 시간이에요.",
        "액션": "꾸준히 준비하세요. 남들이 보지 않아도, 당신이 쌓는 실력은 언젠가 세상을 놀라게 할 거예요."
      },
      {
        "v": 10,
        "타입": "중립",
        "제목": "첫 페이지를 펼치며",
        "본문": "오늘,\n당신의 인생에 새로운 챕터가 시작돼요.\n빈 페이지 위에 첫 문장을 쓰는 기분이에요.\n어떤 이야기를 써 내려갈지,\n모든 선택은 당신의 손에 달려 있어요.\n두려워하지 말고,\n당신만의 이야기를 용기 있게 써 내려가세요.\n오늘은 새로운 인생의 첫 페이지를,\n펼치는 날이에요.",
        "액션": "당신만의 이야기를 시작하세요. 두려움 없이 첫 문장을 쓰면, 세상에 없던 멋진 이야기가 펼쳐질 거예요."
      }
    ],
    "목욕": [
      {
        "v": 1,
        "타입": "심오",
        "제목": "씻고 다듬는 과정",
        "본문": "오늘,\n당신은 목욕탕에 들어가요.\n불순물을 씻어내고,\n진짜 나를 찾는 시간이에요.\n목욕지의 기운,\n끊임없이 다듬고 정돈하는 에너지예요.\n당신은 완벽해지고 싶어 해요.\n흐트러진 모습을 보이기 싫어하고,\n언제나 단정하고 깔끔한 상태를 유지하려 해요.\n오늘은 스스로를 가다듬는,\n소중한 날이에요.",
        "액션": "자신을 정돈하세요. 외모든 마음이든, 깔끔하게 정리하면 세상을 대하는 자신감이 생길 거예요."
      },
      {
        "v": 2,
        "타입": "심오",
        "제목": "멋쟁이의 자부심",
        "본문": "오늘,\n당신의 미적 감각이 빛을 발해요.\n목욕은 씻고 나면 예쁜 옷을 입는 거예요.\n당신은 자신을 아름답게 꾸밀 줄 알아요.\n패션 감각이 뛰어나고,\n유행에 민감해요.\n사람들은 당신의 세련된 스타일을 보고,\n감탄하고 배우려 해요.\n오늘은 당신의 외적인 아름다움이,\n내면의 자신감으로 이어지는 날이에요.",
        "액션": "자신을 꾸며보세요. 당신의 멋스러운 스타일이 세상에 긍정적인 에너지를 전하고, 자신감을 높일 거예요."
      },
      {
        "v": 3,
        "타입": "심오",
        "제목": "시행착오의 아름다움",
        "본문": "오늘,\n당신은 실수할 수 있어요.\n목욕지는 불안정해요.\n한 번에 완벽할 수 없어요.\n하지만 그 시행착오가,\n당신을 더 세련되고 감각적으로 만들어요.\n실패를 두려워하지 마세요.\n여러 번 넘어지고 일어서는 과정이,\n당신을 누구보다 강하고 아름답게 만들 거예요.\n오늘은 실수를 통해 배우는,\n귀한 날이에요.",
        "액션": "실수를 받아들이세요. 완벽하지 않아도 괜찮아요. 시행착오를 통해 당신은 더 빛날 거예요."
      },
      {
        "v": 4,
        "타입": "심오",
        "제목": "나체도화의 진심",
        "본문": "오늘,\n당신의 솔직함이 세상을 움직여요.\n나체도화,\n옷을 벗은 것처럼 투명한 거예요.\n거짓을 숨길 줄 몰라요.\n이 솔직함이 때로는 무기가 되지만,\n사람들의 마음을 여는 가장 강력한 열쇠이기도 해요.\n당신의 진심 어린 한마디가,\n누군가의 인생을 바꿀 수 있어요.\n오늘은 당신의 솔직함이,\n가장 큰 매력이 되는 날이에요.",
        "액션": "진심을 드러내세요. 당신의 솔직한 마음이 사람들에게 신뢰를 주고, 진정한 관계를 만들 거예요."
      },
      {
        "v": 5,
        "타입": "심오",
        "제목": "롤러코스터를 타는 용기",
        "본문": "오늘,\n당신의 감정은 롤러코스터를 타요.\n기분이 좋았다 나빴다 해요.\n목욕지의 변동성이에요.\n하지만 이 파도를 즐겨보세요.\n당신은 그 파도 위에서,\n가장 멋진 서핑을 할 수 있는 사람이에요.\n변화를 두려워하지 말고,\n그 흐름에 몸을 맡기세요.\n오늘은 변화를 즐기는,\n특별한 날이에요.",
        "액션": "변화를 즐기세요. 감정의 기복이 있어도 괜찮아요. 그 파도를 타는 법을 배우면, 인생이 더 흥미로워질 거예요."
      },
      {
        "v": 6,
        "타입": "중립",
        "제목": "정화의 시간",
        "본문": "오늘,\n당신은 마음을 씻어내요.\n쌓였던 피로와 스트레스를,\n물에 흘려보내는 기분이에요.\n가끔은 이렇게 멈춰서,\n자신을 돌보는 시간이 필요해요.\n깨끗이 정화된 마음으로,\n다시 세상을 대하면,\n모든 것이 새롭게 보일 거예요.\n오늘은 스스로를 정화하는,\n귀한 날이에요.",
        "액션": "마음을 비우는 시간을 가지세요. 쌓인 것들을 내려놓으면, 새로운 에너지가 들어올 공간이 생겨요."
      },
      {
        "v": 7,
        "타입": "중립",
        "제목": "다듬어지는 순간",
        "본문": "오늘,\n당신은 조금 더 나은 사람이 돼요.\n어제보다 오늘,\n오늘보다 내일.\n끊임없이 자신을 다듬고 성장하는 중이에요.\n이 과정이 힘들 수 있지만,\n그만큼 당신은 더 빛나게 될 거예요.\n완벽하지 않아도 괜찮아요.\n지금 이 순간,\n당신은 충분히 아름다워요.",
        "액션": "스스로를 사랑하세요. 완벽하지 않은 지금의 모습도 충분히 가치 있고, 아름답다는 것을 기억하세요."
      },
      {
        "v": 8,
        "타입": "중립",
        "제목": "변화의 물결",
        "본문": "오늘,\n작은 변화가 당신을 찾아와요.\n익숙한 것이 조금 달라 보일 수 있어요.\n낯설어도 괜찮아요.\n변화는 성장의 신호예요.\n새로운 것을 받아들이면,\n당신의 삶은 더 풍성해질 거예요.\n변화를 두려워하지 말고,\n그 흐름에 몸을 맡겨보세요.\n오늘은 변화를 맞이하는,\n특별한 날이에요.",
        "액션": "변화를 환영하세요. 낯선 것이 찾아와도, 열린 마음으로 받아들이면 새로운 가능성이 보일 거예요."
      },
      {
        "v": 9,
        "타입": "중립",
        "제목": "감정의 파도",
        "본문": "오늘,\n당신의 감정은 파도처럼 흘러요.\n잔잔했다가 거칠어지기도 해요.\n이 감정의 흐름을 억누르지 마세요.\n느끼는 것을 있는 그대로 받아들이고,\n그 안에서 당신을 발견하세요.\n감정은 당신이 살아있다는 증거예요.\n오늘은 자신의 감정에 솔직해지는,\n용기 있는 날이에요.",
        "액션": "감정을 느끼세요. 기쁨이든 슬픔이든, 있는 그대로 받아들이면 당신은 더 진정성 있는 사람이 될 거예요."
      },
      {
        "v": 10,
        "타입": "중립",
        "제목": "새롭게 태어나는 기분",
        "본문": "오늘,\n당신은 새롭게 태어나는 기분을 느껴요.\n마치 모든 것을 다시 시작하는 것 같아요.\n과거의 무게를 내려놓고,\n가벼운 마음으로 앞으로 나아가세요.\n인생은 언제든 다시 시작할 수 있어요.\n오늘이 바로 그 시작점이 될 수 있어요.\n오늘은 새로운 나를 만나는,\n설레는 날이에요.",
        "액션": "새롭게 시작하세요. 과거에 얽매이지 말고, 지금 이 순간부터 당신이 원하는 삶을 살아가세요."
      }
    ],
    "관대": [
      {
        "v": 1,
        "타입": "심오",
        "제목": "정관의 관을 쓰다",
        "본문": "오늘,\n당신은 명예로운 관을 쓰고 세상 앞에 서요.\n정관의 기운,\n원칙과 명예가 당신을 빛나게 해요.\n당신은 남들 앞에 설 때,\n가장 큰 에너지를 받아요.\n사람들의 시선과 기대가,\n당신을 더욱 단단하게 만들어요.\n오늘은 당신의 리더십이,\n세상에 인정받는 날이에요.",
        "액션": "당당하게 나서세요. 사람들 앞에 설 때 당신은 가장 빛나며, 그 명예를 통해 더 큰 책임감을 얻을 거예요."
      },
      {
        "v": 2,
        "타입": "심오",
        "제목": "백마의 품격",
        "본문": "오늘,\n백마는 품격 있게 걸어요.\n서두르지 않고,\n당당하게 자신의 길을 가요.\n당신은 자신을 함부로 대하지 않아요.\n언제나 단정하고 예의 바르게,\n세상을 대해요.\n이 품격이 사람들에게 존경과 신뢰를 받아요.\n오늘은 당신의 고결함이,\n빛을 발하는 날이에요.",
        "액션": "품격을 유지하세요. 어떤 상황에서도 당당하고 예의 바르게 행동하면, 사람들이 당신을 존중할 거예요."
      },
      {
        "v": 3,
        "타입": "심오",
        "제목": "스포트라이트 아래에서",
        "본문": "오늘,\n당신은 무대 위에 있어요.\n조명이 당신을 비추고,\n사람들의 시선이 집중돼요.\n두려워하지 마세요.\n당신은 그 주목을 받을 자격이 있어요.\n도화의 기운,\n당신의 매력이 사람들을 끌어당겨요.\n오늘은 당신이 주인공이 되는,\n화려한 날이에요.",
        "액션": "주목을 즐기세요. 사람들의 시선을 받을 때 당신은 가장 빛나며, 그 에너지로 더 큰 성과를 낼 거예요."
      },
      {
        "v": 4,
        "타입": "심오",
        "제목": "명예로운 책임",
        "본문": "오늘,\n당신은 큰 책임을 맡아요.\n정관의 무게,\n명예와 함께 오는 의무예요.\n당신은 이 책임을 기꺼이 받아들여요.\n남들이 회피하는 일도,\n당신은 당당히 해내요.\n이 책임감이 당신을 더 큰 사람으로 만들어요.\n오늘은 당신의 리더십이,\n인정받는 날이에요.",
        "액션": "책임을 다하세요. 무거운 짐이라도, 당신이 짊어지면 그것은 명예가 되고 성장의 기회가 될 거예요."
      },
      {
        "v": 5,
        "타입": "심오",
        "제목": "정의로운 리더",
        "본문": "오늘,\n당신은 정의를 실천해요.\n바른 것을 추구하지만,\n맹목적으로 복종하지는 않아요.\n불의를 보면 윗사람에게도,\n직언을 서슴지 않는 기개가 있어요.\n이 정의로움이 당신을 더욱 빛나게 해요.\n오늘은 당신의 원칙이,\n세상을 바꾸는 날이에요.",
        "액션": "정의를 말하세요. 옳은 것을 용기 있게 말하면, 세상이 조금씩 바뀌고 사람들이 당신을 따를 거예요."
      },
      {
        "v": 6,
        "타입": "중립",
        "제목": "인정받는 기쁨",
        "본문": "오늘,\n당신의 노력이 인정받아요.\n사람들이 당신을 알아봐요.\n그동안 쌓아온 성실함과 실력이,\n드디어 빛을 보는 순간이에요.\n자부심을 가지세요.\n당신은 충분히 잘하고 있어요.\n이 인정이 당신에게,\n더 큰 동기부여가 될 거예요.\n오늘은 당신의 가치가,\n세상에 드러나는 날이에요.",
        "액션": "자신감을 가지세요. 사람들의 인정을 겸손하게 받아들이고, 더 높은 목표를 향해 나아가세요."
      },
      {
        "v": 7,
        "타입": "중립",
        "제목": "사회적 역할의 확장",
        "본문": "오늘,\n당신의 역할이 확장돼요.\n더 많은 사람들이 당신을 필요로 해요.\n처음에는 부담스러울 수 있지만,\n이것은 당신이 성장하고 있다는 증거예요.\n새로운 책임을 기꺼이 받아들이세요.\n그 과정에서 당신은,\n더 큰 사람이 될 거예요.\n오늘은 당신의 영향력이,\n커지는 날이에요.",
        "액션": "역할을 받아들이세요. 새로운 책임이 두렵더라도, 그것을 통해 당신은 더 넓은 세상을 경험할 거예요."
      },
      {
        "v": 8,
        "타입": "중립",
        "제목": "자신감의 상승",
        "본문": "오늘,\n당신의 자신감이 올라가요.\n당당하게 의견을 말하고,\n주저 없이 행동할 수 있어요.\n이 자신감이 주변 사람들에게,\n긍정적인 에너지를 전해요.\n당신을 따르는 사람들이 생겨요.\n오늘은 당신의 카리스마가,\n빛을 발하는 날이에요.",
        "액션": "당당하게 말하세요. 자신감 있는 당신의 모습이 사람들에게 영감을 주고, 긍정적인 변화를 만들 거예요."
      },
      {
        "v": 9,
        "타입": "중립",
        "제목": "어른으로서의 품격",
        "본문": "오늘,\n당신은 성숙한 모습을 보여요.\n상황을 냉정하게 판단하고,\n책임감 있게 행동해요.\n사람들이 당신을 믿고 의지해요.\n이 신뢰가 당신에게,\n더 큰 기회를 가져다줄 거예요.\n오늘은 당신의 성숙함이,\n인정받는 날이에요.",
        "액션": "성숙하게 행동하세요. 감정보다 이성으로 판단하면, 사람들이 당신을 더 신뢰하고 따를 거예요."
      },
      {
        "v": 10,
        "타입": "중립",
        "제목": "명예의 무게를 지탱하며",
        "본문": "오늘,\n당신은 명예와 함께 살아가요.\n이름에 걸맞은 행동을 하려 노력해요.\n쉽지 않은 길이지만,\n당신은 그 무게를 견뎌낼 수 있어요.\n명예는 책임이지만,\n동시에 당신을 지켜주는 방패이기도 해요.\n오늘은 당신의 명예가,\n빛을 발하는 날이에요.",
        "액션": "명예를 지키세요. 당신의 이름에 걸맞게 행동하면, 세상이 당신을 존중하고 기회를 줄 거예요."
      }
    ],
    "건록": [
      {
        "v": 1,
        "타입": "심오",
        "제목": "제련된 명검",
        "본문": "오늘,\n달궈진 쇠가 마침내 명검이 돼요.\n용광로 속에서,\n수없이 단련된 결과예요.\n庚금이 午화를 만나,\n가장 단단하고 예리한 상태가 됐어요.\n당신의 실력이 정점에 달했어요.\n이제는 그 실력을 세상에 보여줄 때예요.\n오늘은 당신의 전문성이,\n인정받는 날이에요.",
        "액션": "실력을 발휘하세요. 갈고닦은 당신의 능력을 마음껏 펼치면, 세상이 놀라고 기회가 찾아올 거예요."
      },
      {
        "v": 2,
        "타입": "심오",
        "제목": "완벽주의의 결실",
        "본문": "오늘,\n당신의 완벽주의가 빛을 발해요.\n남들이 쉴 때도,\n자신을 갈고닦는 것을 멈추지 않았어요.\n그 노력이 드디어 결실을 맺어요.\n완벽에 가까운 결과물이,\n사람들에게 감동을 줘요.\n오늘은 당신의 자기 관리가,\n최고의 성과로 이어지는 날이에요.",
        "액션": "완벽을 추구하세요. 디테일에 신경 쓰는 당신의 노력이 결국 최고의 결과를 만들어낼 거예요."
      },
      {
        "v": 3,
        "타입": "심오",
        "제목": "정직함의 힘",
        "본문": "오늘,\n당신의 정직함이 큰 힘이 돼요.\n거짓 없이 살아온 당신,\n사람들이 그 진정성을 알아봐요.\n나체도화의 솔직함이,\n세상에서 가장 강력한 무기가 돼요.\n당신의 한마디가,\n사람들의 마음을 움직이고 신뢰를 만들어요.\n오늘은 당신의 진심이,\n세상을 바꾸는 날이에요.",
        "액션": "진심을 말하세요. 거짓 없는 당신의 말이 사람들에게 깊은 감동을 주고, 진정한 관계를 만들 거예요."
      },
      {
        "v": 4,
        "타입": "심오",
        "제목": "백마의 전성기",
        "본문": "오늘,\n백마는 전성기를 맞이해요.\n가장 빠르고,\n가장 아름답게 달려요.\n모든 사람들의 시선이,\n당신에게 집중돼요.\n이 순간을 즐기세요.\n당신의 매력과 실력이,\n최고조에 달한 시간이에요.\n오늘은 당신이 세상의 중심이 되는,\n빛나는 날이에요.",
        "액션": "최선을 다하세요. 지금이 당신의 전성기예요. 이 순간을 놓치지 말고, 모든 것을 쏟아부으세요."
      },
      {
        "v": 5,
        "타입": "심오",
        "제목": "정의의 실천",
        "본문": "오늘,\n당신은 정의를 실천할 힘을 가졌어요.\n더 이상 말만 하지 않아요.\n직접 행동으로 옮겨요.\n불의를 보면 참지 않고,\n옳은 일을 위해 나서요.\n당신의 용기가,\n세상을 조금씩 바꿔요.\n오늘은 당신의 정의로움이,\n현실이 되는 날이에요.",
        "액션": "행동하세요. 옳다고 생각하는 것을 실천에 옮기면, 당신의 정의가 세상을 변화시킬 거예요."
      },
      {
        "v": 6,
        "타입": "중립",
        "제목": "능력의 정점",
        "본문": "오늘,\n당신의 능력이 정점에 달해요.\n그동안 갈고닦은 실력이,\n드디어 빛을 발해요.\n자신감을 가지고,\n당당하게 실력을 펼쳐 보이세요.\n사람들이 당신의 능력에,\n감탄하고 인정할 거예요.\n오늘은 당신이 최고의 모습을 보여주는,\n멋진 날이에요.",
        "액션": "능력을 발휘하세요. 주저하지 말고 당신의 실력을 보여주면, 세상이 당신을 알아보고 기회를 줄 거예요."
      },
      {
        "v": 7,
        "타입": "중립",
        "제목": "수확의 기쁨",
        "본문": "오늘,\n당신이 뿌린 씨앗이 열매를 맺어요.\n그동안의 노력이,\n드디어 결실로 돌아와요.\n기쁨을 만끽하세요.\n당신은 이 순간을 누릴 자격이 있어요.\n하지만 여기서 멈추지 마세요.\n이것은 끝이 아니라,\n새로운 시작이에요.",
        "액션": "성과를 즐기세요. 당신이 이룬 것을 자랑스럽게 여기고, 다음 목표를 향해 또 나아가세요."
      },
      {
        "v": 8,
        "타입": "중립",
        "제목": "에너지의 충만",
        "본문": "오늘,\n당신은 에너지가 넘쳐요.\n무엇이든 할 수 있을 것 같아요.\n이 충만한 에너지를,\n좋은 곳에 쓰세요.\n당신이 움직이면,\n세상도 함께 움직여요.\n오늘은 당신의 활력이,\n주변에 긍정적인 영향을 주는 날이에요.",
        "액션": "적극적으로 행동하세요. 넘치는 에너지를 좋은 일에 쓰면, 당신과 주변 모두에게 행복이 찾아올 거예요."
      },
      {
        "v": 9,
        "타입": "중립",
        "제목": "영향력의 확대",
        "본문": "오늘,\n당신의 영향력이 커져요.\n더 많은 사람들이,\n당신의 말에 귀 기울여요.\n이 영향력을 책임감 있게 사용하세요.\n당신의 한마디가,\n누군가의 인생을 바꿀 수 있어요.\n오늘은 당신의 목소리가,\n세상에 울려 퍼지는 날이에요.",
        "액션": "영향력을 행사하세요. 좋은 메시지를 전하면, 당신의 말이 많은 사람들에게 희망과 용기를 줄 거예요."
      },
      {
        "v": 10,
        "타입": "중립",
        "제목": "전성기를 달리다",
        "본문": "오늘,\n당신은 전성기를 달리고 있어요.\n모든 것이 순조롭고,\n하는 일마다 잘 풀려요.\n이 순간을 최대한 활용하세요.\n전성기는 영원하지 않지만,\n지금 이 순간의 경험이,\n평생의 자산이 될 거예요.\n오늘은 당신의 최고의 순간을,\n만끽하는 날이에요.",
        "액션": "전성기를 즐기세요. 지금의 행복과 성공을 충분히 누리면서, 미래를 위한 준비도 함께하세요."
      }
    ],
    "제왕": [
      {
        "v": 1,
        "타입": "심오",
        "제목": "왕관을 쓴 백마",
        "본문": "오늘,\n백마는 왕관을 쓰고 세상을 호령해요.\n정관의 최고점,\n명예와 권력이 당신의 것이 됐어요.\n모든 사람들이 당신을 우러러봐요.\n하지만 교만하지 마세요.\n왕관은 영광이지만,\n동시에 무거운 책임이기도 해요.\n오늘은 당신이 최고의 자리에서,\n겸손함을 배우는 날이에요.",
        "액션": "겸손하게 이끌어가세요. 최고의 자리에서도 겸손함을 잃지 않으면, 사람들이 진심으로 따를 거예요."
      },
      {
        "v": 2,
        "타입": "심오",
        "제목": "용광로의 최고온",
        "본문": "오늘,\n용광로가 최고 온도에 달해요.\n너무 뜨거워서,\n녹아내릴 것 같아요.\n庚금이 午화를 만나,\n극한의 상황이에요.\n하지만 이 열기를 견뎌내면,\n세상에서 가장 단단한 명검이 돼요.\n오늘은 극한을 견디는,\n인내의 날이에요.",
        "액션": "견뎌내세요. 지금이 가장 힘든 순간이지만, 이것을 넘으면 당신은 누구도 이길 수 없는 존재가 될 거예요."
      },
      {
        "v": 3,
        "타입": "심오",
        "제목": "완벽의 덫",
        "본문": "오늘,\n당신은 완벽에 가까워졌어요.\n하지만 조심하세요.\n완벽주의가 지나치면,\n스스로를 옭아매는 덫이 될 수 있어요.\n가끔은 불완전함을 받아들이세요.\n당신의 빈틈이,\n오히려 사람들에게 친근함을 줄 거예요.\n오늘은 완벽 속에서,\n여유를 찾는 날이에요.",
        "액션": "여유를 가지세요. 완벽하지 않아도 괜찮아요. 가끔은 실수하는 당신의 모습이 더 매력적일 수 있어요."
      },
      {
        "v": 4,
        "타입": "심오",
        "제목": "스포트라이트의 중심",
        "본문": "오늘,\n모든 조명이 당신을 비춰요.\n도화의 최고점,\n당신은 스타예요.\n사람들이 당신을 따르고,\n동경해요.\n하지만 인기에 취하지 마세요.\n진짜 중요한 것은,\n실력과 인격이에요.\n오늘은 명성 속에서,\n본질을 잃지 않는 날이에요.",
        "액션": "본질에 집중하세요. 인기와 명성은 일시적이지만, 당신의 진정한 가치는 영원히 남을 거예요."
      },
      {
        "v": 5,
        "타입": "심오",
        "제목": "정의의 왕국",
        "본문": "오늘,\n당신은 정의로운 왕국을 다스려요.\n공정하고 투명하게,\n세상을 이끌어가요.\n당신의 정직함과 원칙이,\n사람들에게 신뢰를 줘요.\n하지만 너무 엄격하면,\n사람들이 숨을 못 쉬어요.\n오늘은 정의와 온정 사이의,\n균형을 찾는 날이에요.",
        "액션": "균형을 잡으세요. 원칙도 중요하지만, 사람의 마음을 헤아리는 온정도 함께 베풀어야 진정한 리더예요."
      },
      {
        "v": 6,
        "타입": "중립",
        "제목": "정점에 서다",
        "본문": "오늘,\n당신은 정점에 서 있어요.\n더 이상 오를 곳이 없을 것 같아요.\n하지만 여기서 멈추지 마세요.\n정점은 끝이 아니라,\n새로운 시작이에요.\n이제는 더 높은 곳이 아니라,\n더 깊은 곳으로 나아갈 때예요.\n오늘은 성공의 의미를,\n다시 생각해보는 날이에요.",
        "액션": "더 깊이 생각하세요. 높은 곳에 올랐다면, 이제는 그 의미를 되새기고 더 가치 있는 것을 추구하세요."
      },
      {
        "v": 7,
        "타입": "중립",
        "제목": "권력의 무게",
        "본문": "오늘,\n당신은 큰 권력을 쥐었어요.\n많은 것을 결정할 수 있어요.\n하지만 권력에는,\n그만큼의 책임이 따라와요.\n신중하게 판단하고,\n공정하게 행동하세요.\n당신의 결정이,\n많은 사람들의 삶에 영향을 미쳐요.\n오늘은 권력을 책임감 있게 사용하는,\n귀한 날이에요.",
        "액션": "책임감을 가지세요. 권력을 사심 없이 사용하면, 당신은 존경받는 리더가 될 거예요."
      },
      {
        "v": 8,
        "타입": "중립",
        "제목": "최고의 순간",
        "본문": "오늘,\n당신은 최고의 순간을 살고 있어요.\n모든 것이 완벽해 보여요.\n이 순간을 마음에 새기세요.\n인생에서 이런 순간은,\n자주 오지 않아요.\n하지만 영원할 수는 없어요.\n오늘의 영광을 겸손하게 받아들이고,\n다가올 변화를 준비하세요.",
        "액션": "순간을 기억하세요. 지금의 행복을 마음에 새기고, 앞으로 올 어려움을 견딜 힘으로 삼으세요."
      },
      {
        "v": 9,
        "타입": "중립",
        "제목": "모두가 주목하는 자리",
        "본문": "오늘,\n모든 사람들이 당신을 봐요.\n주목의 중심에 서 있어요.\n부담스러울 수 있지만,\n당신은 그럴 자격이 있어요.\n자신감을 가지고,\n당당하게 서 있으세요.\n당신의 존재 자체가,\n많은 사람들에게 영감을 줘요.",
        "액션": "당당하게 서세요. 사람들의 시선을 두려워하지 말고, 그들에게 긍정적인 영향을 주는 존재가 되세요."
      },
      {
        "v": 10,
        "타입": "중립",
        "제목": "영광의 정점에서",
        "본문": "오늘,\n당신은 영광의 정점에 있어요.\n그동안의 모든 노력이,\n이 순간으로 모였어요.\n축하받을 자격이 충분해요.\n하지만 정점 다음에는,\n내려가는 길도 있다는 것을 기억하세요.\n오늘의 영광에 취하지 말고,\n겸손함으로 미래를 준비하세요.",
        "액션": "겸손을 잃지 마세요. 지금의 영광을 감사하게 받아들이되, 언제나 배우는 자세로 미래를 준비하세요."
      }
    ],
    "쇠": [
      {
        "v": 1,
        "타입": "심오",
        "제목": "식어가는 쇠",
        "본문": "오늘,\n뜨거웠던 쇠가 식기 시작해요.\n용광로에서 나온 명검이,\n조금씩 온도를 잃어요.\n하지만 이것은 실패가 아니에요.\n식는 과정에서,\n진짜 단단함이 완성돼요.\n오늘은 열기를 내려놓고,\n차분함을 얻는 날이에요.",
        "액션": "차분해지세요. 뜨거웠던 열정을 잠시 내려놓고, 냉정하게 주변을 돌아보는 시간을 가지세요."
      },
      {
        "v": 2,
        "타입": "심오",
        "제목": "내려놓는 왕관",
        "본문": "오늘,\n당신은 왕관을 내려놓아요.\n정관의 기운이 약해지고,\n명예가 조금씩 멀어져요.\n하지만 슬퍼하지 마세요.\n왕관의 무게에서 벗어나,\n자유를 얻는 순간이기도 해요.\n오늘은 명예보다,\n내면의 평화를 찾는 날이에요.",
        "액션": "자유를 느껴보세요. 명예와 책임에서 벗어나, 진짜 당신이 원하는 것이 무엇인지 생각해보세요."
      },
      {
        "v": 3,
        "타입": "심오",
        "제목": "완벽주의의 피로",
        "본문": "오늘,\n당신은 조금 지쳤어요.\n늘 완벽하려 애쓰는 것이,\n이제는 버거워요.\n가끔은 불완전해도 괜찮아요.\n스스로에게 너그러워지세요.\n쉬는 것도 용기예요.\n오늘은 자신을 돌아보고,\n여유를 찾는 날이에요.",
        "액션": "쉬어가세요. 늘 완벽할 필요는 없어요. 지친 마음을 달래고, 스스로를 위로하는 시간을 가지세요."
      },
      {
        "v": 4,
        "타입": "심오",
        "제목": "조명이 꺼진 무대",
        "본문": "오늘,\n화려했던 조명이 꺼져요.\n사람들의 시선이,\n다른 곳으로 향해요.\n도화의 기운이 약해지고,\n주목받지 못하는 것 같아요.\n하지만 이것도 괜찮아요.\n조명 없이도,\n당신은 여전히 빛나는 사람이에요.",
        "액션": "본질에 집중하세요. 다른 사람의 시선이 아니라, 당신 자신의 가치를 돌아보는 시간이에요."
      },
      {
        "v": 5,
        "타입": "심오",
        "제목": "정의의 회의",
        "본문": "오늘,\n당신은 정의에 대해 회의를 느껴요.\n옳은 일을 했는데,\n돌아오는 것은 상처뿐이에요.\n하지만 포기하지 마세요.\n당신의 정의는,\n언젠가 빛을 볼 거예요.\n오늘은 흔들리는 믿음을,\n다시 세우는 날이에요.",
        "액션": "믿음을 지키세요. 지금은 힘들어도, 당신의 정의로움이 결국 세상을 바꿀 거라는 믿음을 잃지 마세요."
      },
      {
        "v": 6,
        "타입": "중립",
        "제목": "에너지의 감소",
        "본문": "오늘,\n당신의 에너지가 조금 줄어들어요.\n무기력함이 찾아올 수 있어요.\n억지로 힘을 내려 하지 마세요.\n가끔은 쉬는 것도,\n필요한 과정이에요.\n충전의 시간을 가지세요.\n오늘은 멈추고,\n자신을 돌보는 날이에요.",
        "액션": "충분히 쉬세요. 에너지가 떨어졌을 때는 억지로 달리지 말고, 충전하는 시간을 가지세요."
      },
      {
        "v": 7,
        "타입": "중립",
        "제목": "작은 후퇴",
        "본문": "오늘,\n조금 뒤로 물러나게 될 수 있어요.\n진전이 더뎌지거나,\n일이 생각대로 안 풀릴 수 있어요.\n하지만 이것은 실패가 아니에요.\n후퇴도 전진의 한 방법이에요.\n오늘은 한 발 물러서서,\n상황을 다시 보는 날이에요.",
        "액션": "여유를 가지세요. 뒤로 물러나는 것도 때로는 필요해요. 거리를 두면 새로운 관점이 보일 거예요."
      },
      {
        "v": 8,
        "타입": "중립",
        "제목": "인기의 하락",
        "본문": "오늘,\n사람들의 관심이 조금 줄어들 수 있어요.\n예전만큼 주목받지 못하는 것 같아요.\n하지만 괜찮아요.\n진짜 중요한 것은,\n남들의 시선이 아니라 당신 자신이에요.\n오늘은 외부의 평가보다,\n내면의 가치를 돌아보는 날이에요.",
        "액션": "자신을 믿으세요. 다른 사람의 관심이 줄어들어도, 당신의 가치는 변하지 않아요."
      },
      {
        "v": 9,
        "타입": "중립",
        "제목": "피로의 누적",
        "본문": "오늘,\n쌓인 피로가 느껴져요.\n그동안 너무 열심히 달려왔어요.\n이제는 쉬어야 할 때예요.\n몸과 마음이 보내는 신호를,\n무시하지 마세요.\n오늘은 자신을 위한,\n휴식의 날로 만드세요.",
        "액션": "충분히 쉬세요. 피로를 방치하면 더 큰 문제가 될 수 있어요. 지금 당장 멈추고 쉬는 용기를 내세요."
      },
      {
        "v": 10,
        "타입": "중립",
        "제목": "조용한 반성",
        "본문": "오늘,\n조용히 자신을 돌아보는 시간을 가져요.\n그동안 너무 앞만 보고 달렸어요.\n이제는 뒤를 돌아보고,\n무엇을 놓쳤는지 생각해볼 때예요.\n반성은 성장의 시작이에요.\n오늘은 과거를 돌아보며,\n미래를 준비하는 날이에요.",
        "액션": "자신을 돌아보세요. 지나온 길을 되짚어보면, 앞으로 나아갈 방향이 더 명확하게 보일 거예요."
      }
    ],
    "병": [
      {
        "v": 1,
        "타입": "심오",
        "제목": "녹슨 명검",
        "본문": "오늘,\n명검이 녹슬기 시작해요.\n庚금이 午화에 너무 오래 노출됐어요.\n빛을 잃고,\n예리함이 무뎌져요.\n하지만 포기하지 마세요.\n다시 갈고닦으면,\n예전의 빛을 되찾을 수 있어요.\n오늘은 자신을 돌보고,\n회복하는 날이에요.",
        "액션": "자신을 돌보세요. 지금은 힘들어도, 관리하고 정비하면 다시 빛날 수 있어요."
      },
      {
        "v": 2,
        "타입": "심오",
        "제목": "완벽주의의 독",
        "본문": "오늘,\n완벽을 향한 집착이 당신을 아프게 해요.\n모든 것을 완벽하게 하려다,\n정작 자신은 돌보지 못했어요.\n이제는 내려놓을 때예요.\n완벽하지 않아도,\n당신은 충분히 가치 있어요.\n오늘은 완벽주의를 내려놓고,\n자신을 용서하는 날이에요.",
        "액션": "자신을 용서하세요. 완벽하지 않은 것이 인간이에요. 스스로에게 너그러워지는 연습을 하세요."
      },
      {
        "v": 3,
        "타입": "심오",
        "제목": "솔직함의 상처",
        "본문": "오늘,\n당신의 솔직함이 상처가 돼 돌아와요.\n진심을 말했는데,\n오해를 받았어요.\n나체도화의 투명함이,\n때로는 약점이 될 수 있어요.\n하지만 후회하지 마세요.\n거짓 없이 산 당신은,\n떳떳해요.\n오늘은 상처를 치유하는,\n따뜻한 날이에요.",
        "액션": "상처를 치유하세요. 진심으로 살았다면, 그것만으로 충분해요. 시간이 당신의 진심을 증명해줄 거예요."
      },
      {
        "v": 4,
        "타입": "심오",
        "제목": "빛 바랜 백마",
        "본문": "오늘,\n백마는 지쳤어요.\n더 이상 빠르게 달릴 수 없어요.\n화려했던 모습은 사라지고,\n초라함만 남았어요.\n하지만 이것도 지나갈 거예요.\n쉬면서 회복하면,\n다시 달릴 수 있어요.\n오늘은 멈추고,\n치유하는 날이에요.",
        "액션": "충분히 쉬세요. 지금은 달릴 때가 아니에요. 멈추고 회복하면, 언젠가 다시 달릴 수 있어요."
      },
      {
        "v": 5,
        "타입": "심오",
        "제목": "정의의 좌절",
        "본문": "오늘,\n정의가 패배한 것 같아요.\n옳은 일을 했는데,\n아무도 알아주지 않아요.\n억울하고 분해요.\n하지만 포기하지 마세요.\n당신의 정의는,\n언젠가 빛을 볼 거예요.\n오늘은 상처받은 마음을,\n어루만지는 날이에요.",
        "액션": "마음을 어루만지세요. 지금은 힘들어도, 당신의 정의로움은 결국 인정받을 거라는 믿음을 가지세요."
      },
      {
        "v": 6,
        "타입": "중립",
        "제목": "몸의 신호",
        "본문": "오늘,\n당신의 몸이 신호를 보내요.\n쉬라고,\n멈추라고 말해요.\n무시하지 마세요.\n건강을 잃으면,\n모든 것을 잃어요.\n오늘은 몸의 소리에 귀 기울이고,\n충분한 휴식을 취하는 날이에요.",
        "액션": "건강을 챙기세요. 몸이 아프면 아무것도 할 수 없어요. 지금 당장 쉬고, 병원에 가보세요."
      },
      {
        "v": 7,
        "타입": "중립",
        "제목": "마음의 감기",
        "본문": "오늘,\n마음이 감기에 걸렸어요.\n우울하고,\n무기력해요.\n혼자 끙끙 앓지 마세요.\n누군가에게 말하고,\n도움을 청하세요.\n오늘은 마음의 병을,\n치료하는 날이에요.",
        "액션": "도움을 청하세요. 혼자 견디려 하지 말고, 주변 사람이나 전문가에게 도움을 요청하세요."
      },
      {
        "v": 8,
        "타입": "중립",
        "제목": "작은 불편함",
        "본문": "오늘,\n작은 불편함이 느껴져요.\n크게 아프지는 않지만,\n뭔가 개운하지 않아요.\n이럴 때일수록,\n자신을 잘 돌봐야 해요.\n작은 신호를 무시하면,\n큰 병이 될 수 있어요.\n오늘은 자신을 세심하게,\n살피는 날이에요.",
        "액션": "세심하게 살피세요. 작은 불편함도 무시하지 말고, 원인을 찾아 미리 대처하세요."
      },
      {
        "v": 9,
        "타입": "중립",
        "제목": "회복의 시작",
        "본문": "오늘,\n회복이 시작돼요.\n아팠던 몸과 마음이,\n조금씩 나아지고 있어요.\n서두르지 마세요.\n회복에는 시간이 필요해요.\n천천히,\n자신의 속도에 맞춰 나아가세요.\n오늘은 희망을 품고,\n치유하는 날이에요.",
        "액션": "천천히 회복하세요. 급하게 서두르지 말고, 자신의 속도에 맞춰 조금씩 나아가세요."
      },
      {
        "v": 10,
        "타입": "중립",
        "제목": "병상의 깨달음",
        "본문": "오늘,\n아픔 속에서 깨달음을 얻어요.\n건강할 때는 몰랐던 것들이,\n이제야 보여요.\n무엇이 진짜 소중한지,\n누가 진짜 내 편인지.\n오늘은 아픔을 통해,\n인생을 배우는 날이에요.",
        "액션": "배움을 얻으세요. 아픔도 선생님이에요. 이 경험을 통해 더 지혜로운 사람이 되세요."
      }
    ],
    "사": [
      {
        "v": 1,
        "타입": "심오",
        "제목": "쇠의 죽음",
        "본문": "오늘,\n쇠가 완전히 녹아내려요.\n庚금이 午화에 극을 당해요.\n형체를 잃고,\n존재가 사라지는 것 같아요.\n하지만 이것은 끝이 아니에요.\n죽음은 새로운 탄생의 시작이에요.\n오늘은 낡은 것을 버리고,\n새로운 나로 거듭나는 날이에요.",
        "액션": "과거를 놓아주세요. 낡은 것에 집착하지 말고, 과감하게 버리면 새로운 당신이 태어날 거예요."
      },
      {
        "v": 2,
        "타입": "심오",
        "제목": "완벽주의의 죽음",
        "본문": "오늘,\n완벽주의를 죽여야 해요.\n더 이상 완벽할 수 없어요.\n모든 것이 무너져 내려요.\n하지만 이것이 자유의 시작이에요.\n완벽하지 않아도 괜찮다는 것을,\n받아들이는 순간,\n진짜 삶이 시작돼요.\n오늘은 완벽의 환상에서,\n깨어나는 날이에요.",
        "액션": "환상을 깨세요. 완벽은 환상이에요. 불완전한 당신을 있는 그대로 받아들이면, 진짜 자유가 올 거예요."
      },
      {
        "v": 3,
        "타입": "심오",
        "제목": "명예의 죽음",
        "본문": "오늘,\n당신의 명예가 땅에 떨어져요.\n정관이 사라지고,\n사람들의 존경도 사라져요.\n모든 것을 잃은 것 같아요.\n하지만 이제야 진짜를 볼 수 있어요.\n명예 없이도,\n당신은 여전히 가치 있는 사람이에요.\n오늘은 진짜 나를 발견하는,\n귀한 날이에요.",
        "액션": "진짜 나를 찾으세요. 명예와 지위를 벗어던진 후에야, 진정한 당신을 발견할 수 있어요."
      },
      {
        "v": 4,
        "타입": "심오",
        "제목": "백마의 최후",
        "본문": "오늘,\n백마는 더 이상 달리지 못해요.\n지친 다리,\n흐려진 눈.\n모든 것이 끝난 것 같아요.\n하지만 이것은 쉼표예요.\n마침표가 아니에요.\n오늘은 긴 여정을 마무리하고,\n다음 여정을 준비하는 날이에요.",
        "액션": "쉼표를 찍으세요. 지금은 멈춰야 할 때예요. 충분히 쉬고 나면, 새로운 길이 보일 거예요."
      },
      {
        "v": 5,
        "타입": "심오",
        "제목": "정의의 패배",
        "본문": "오늘,\n정의가 패배했어요.\n불의가 승리한 것 같아요.\n당신의 싸움이,\n헛된 것 같아요.\n하지만 포기하지 마세요.\n진짜 정의는,\n결과가 아니라 과정에 있어요.\n오늘은 패배 속에서,\n더 큰 의미를 찾는 날이에요.",
        "액션": "의미를 찾으세요. 결과가 아니라, 당신이 싸웠다는 사실 자체에 의미가 있어요."
      },
      {
        "v": 6,
        "타입": "중립",
        "제목": "끝과 시작 사이",
        "본문": "오늘,\n당신은 끝과 시작 사이에 있어요.\n뭔가 끝났지만,\n아직 새로운 것은 시작되지 않았어요.\n불안하고 막막해요.\n하지만 이 과도기를 견뎌내세요.\n모든 끝은,\n새로운 시작의 전조예요.\n오늘은 기다리며,\n준비하는 날이에요.",
        "액션": "기다리세요. 조급해하지 말고, 새로운 시작이 올 때까지 차분히 준비하세요."
      },
      {
        "v": 7,
        "타입": "중립",
        "제목": "모든 것을 내려놓다",
        "본문": "오늘,\n모든 것을 내려놓으세요.\n집착했던 것들,\n붙잡고 있던 것들.\n다 놓아주세요.\n비워야,\n새로운 것이 들어올 수 있어요.\n오늘은 과거를 정리하고,\n미래를 위한 공간을 만드는 날이에요.",
        "액션": "내려놓으세요. 집착을 버리고 손을 펴면, 새로운 것을 받아들일 준비가 될 거예요."
      },
      {
        "v": 8,
        "타입": "중립",
        "제목": "깊은 침묵",
        "본문": "오늘,\n깊은 침묵 속에 잠겨요.\n말하고 싶지 않아요.\n움직이고 싶지도 않아요.\n괜찮아요.\n가끔은 이렇게,\n완전히 멈추는 것도 필요해요.\n오늘은 침묵 속에서,\n자신과 대화하는 날이에요.",
        "액션": "침묵하세요. 말없이 자신과 마주하는 시간을 가지면, 내면의 소리가 들릴 거예요."
      },
      {
        "v": 9,
        "타입": "중립",
        "제목": "존재의 의미",
        "본문": "오늘,\n당신은 존재의 의미를 묻게 돼요.\n왜 사는지,\n무엇을 위해 사는지.\n답이 쉽게 나오지 않아요.\n하지만 이 질문 자체가 중요해요.\n오늘은 인생의 본질을,\n깊이 생각하는 날이에요.",
        "액션": "질문하세요. 쉬운 답은 없지만, 질문을 멈추지 않으면 언젠가 당신만의 답을 찾을 거예요."
      },
      {
        "v": 10,
        "타입": "중립",
        "제목": "마지막 쉼표",
        "본문": "오늘,\n긴 문장의 끝에 쉼표를 찍어요.\n한 챕터가 끝나요.\n슬프지만,\n동시에 해방감도 느껴져요.\n이제 새로운 챕터가,\n기다리고 있어요.\n오늘은 지나온 길을 정리하고,\n새로운 페이지를 펼칠 준비를 하는 날이에요.",
        "액션": "정리하세요. 지나온 것을 정리하고 마무리하면, 새로운 시작을 위한 마음의 공간이 생길 거예요."
      }
    ],
    "묘": [
      {
        "v": 1,
        "타입": "심오",
        "제목": "쇠의 무덤",
        "본문": "오늘,\n쇠가 땅속 깊이 묻혀요.\n庚금이 午화에 완전히 극을 당한 후,\n조용히 안치돼요.\n어둡고 고요해요.\n하지만 이 무덤 속에서,\n새로운 생명이 준비되고 있어요.\n오늘은 깊은 휴식과,\n재생의 날이에요.",
        "액션": "깊이 쉬세요. 완전히 멈추고 어둠 속에 머물면, 그 안에서 새로운 에너지가 모일 거예요."
      },
      {
        "v": 2,
        "타입": "심오",
        "제목": "명예를 묻다",
        "본문": "오늘,\n당신은 명예를 땅에 묻어요.\n정관을 포기하고,\n세상의 시선에서 벗어나요.\n외롭고 쓸쓸해요.\n하지만 이 고독 속에서,\n진짜 자유를 발견해요.\n오늘은 세상의 기대를 내려놓고,\n진정한 나를 찾는 날이에요.",
        "액션": "고독을 받아들이세요. 혼자만의 시간 속에서 당신은 진정한 자신과 만날 수 있어요."
      },
      {
        "v": 3,
        "타입": "심오",
        "제목": "완벽의 장례",
        "본문": "오늘,\n완벽주의를 장사 지내요.\n더 이상 완벽을 추구하지 않아요.\n그것이 환상이었다는 것을,\n이제야 깨달았어요.\n해방감이 느껴져요.\n오늘은 완벽의 굴레에서 벗어나,\n있는 그대로의 삶을 시작하는 날이에요.",
        "액션": "있는 그대로 사세요. 완벽을 버리고 나면, 진짜 삶이 얼마나 아름다운지 알게 될 거예요."
      },
      {
        "v": 4,
        "타입": "심오",
        "제목": "백마의 안식",
        "본문": "오늘,\n백마는 마구간에서 편히 쉬어요.\n더 이상 달리지 않아요.\n세상의 주목도,\n사람들의 환호도 필요 없어요.\n조용한 안식만 있으면 돼요.\n오늘은 모든 것을 내려놓고,\n평화를 누리는 날이에요.",
        "액션": "평화를 누리세요. 달리기를 멈추고 고요함 속에 머물면, 진정한 안식을 얻을 거예요."
      },
      {
        "v": 5,
        "타입": "심오",
        "제목": "정의의 무덤",
        "본문": "오늘,\n정의를 무덤에 묻어요.\n더 이상 싸우지 않아요.\n지쳤어요.\n이제는 쉬고 싶어요.\n하지만 이 휴식이,\n영원한 포기는 아니에요.\n오늘은 재충전을 위해,\n잠시 칼을 내려놓는 날이에요.",
        "액션": "칼을 내려놓으세요. 지금은 싸울 때가 아니에요. 충분히 쉬고 나면, 다시 일어설 힘이 생길 거예요."
      },
      {
        "v": 6,
        "타입": "중립",
        "제목": "깊은 어둠 속에서",
        "본문": "오늘,\n당신은 깊은 어둠 속에 있어요.\n앞이 보이지 않아요.\n두렵고 불안해요.\n하지만 어둠도 나쁘지 않아요.\n어둠 속에서야,\n진짜 빛의 소중함을 알게 돼요.\n오늘은 어둠을 견디며,\n빛을 기다리는 날이에요.",
        "액션": "어둠을 견디세요. 지금은 어둡지만, 반드시 빛이 올 거예요. 그때까지 버티세요."
      },
      {
        "v": 7,
        "타입": "중립",
        "제목": "고요한 침잠",
        "본문": "오늘,\n당신은 고요 속에 침잠해요.\n세상과 단절된 기분이에요.\n혼자인 것 같아요.\n하지만 이 고요함이,\n당신을 치유하고 있어요.\n오늘은 세상의 소음에서 벗어나,\n내면의 평화를 찾는 날이에요.",
        "액션": "고요함을 즐기세요. 혼자만의 시간을 두려워하지 말고, 그 안에서 평화를 발견하세요."
      },
      {
        "v": 8,
        "타입": "중립",
        "제목": "잊혀진 기억",
        "본문": "오늘,\n과거의 기억들이 떠올라요.\n좋았던 순간들,\n아팠던 순간들.\n모두 멀게만 느껴져요.\n이제는 놓아줄 때예요.\n오늘은 과거를 정리하고,\n새로운 미래를 준비하는 날이에요.",
        "액션": "과거를 정리하세요. 좋은 기억도 나쁜 기억도, 이제는 놓아주고 앞으로 나아가세요."
      },
      {
        "v": 9,
        "타입": "중립",
        "제목": "무덤 속의 씨앗",
        "본문": "오늘,\n당신은 무덤 속 씨앗이에요.\n아직 싹을 틀 때가 아니에요.\n어둠 속에서,\n힘을 모으고 있어요.\n조급해하지 마세요.\n때가 되면,\n당신은 땅을 뚫고 나올 거예요.\n오늘은 숨죽이며,\n준비하는 날이에요.",
        "액션": "준비하세요. 지금은 보이지 않지만, 땅속에서 힘을 모으면 언젠가 싹을 틔울 거예요."
      },
      {
        "v": 10,
        "타입": "중립",
        "제목": "긴 밤의 끝",
        "본문": "오늘,\n긴 밤이 저물어 가요.\n아직 해는 뜨지 않았지만,\n동쪽 하늘이 조금씩 밝아져요.\n희망이 보여요.\n곧 새로운 아침이 올 거예요.\n오늘은 밤의 끝에서,\n아침을 기다리는 날이에요.",
        "액션": "희망을 가지세요. 가장 어두운 시간이 지나가고 있어요. 조금만 더 버티면 새벽이 올 거예요."
      }
    ],
    "절": [
      {
        "v": 1,
        "타입": "심오",
        "제목": "끊어진 연결",
        "본문": "오늘,\n모든 연결이 끊어져요.\n庚금과 午화의 관계가,\n완전히 단절돼요.\n혼자가 된 것 같아요.\n하지만 이 단절이,\n새로운 연결의 시작이에요.\n오늘은 낡은 인연을 정리하고,\n새로운 인연을 기다리는 날이에요.",
        "액션": "정리하세요. 끊어진 인연에 집착하지 말고, 새로운 만남을 위한 공간을 만드세요."
      },
      {
        "v": 2,
        "타입": "심오",
        "제목": "완벽의 단절",
        "본문": "오늘,\n완벽과의 인연이 끊어져요.\n더 이상 완벽을 추구하지 않아요.\n그것과 결별해요.\n해방감이 느껴져요.\n이제는 자유롭게,\n불완전한 삶을 살 수 있어요.\n오늘은 완벽주의와 이별하고,\n진짜 삶을 시작하는 날이에요.",
        "액션": "자유로워지세요. 완벽의 굴레에서 벗어나면, 진정한 자유와 행복을 느낄 거예요."
      },
      {
        "v": 3,
        "타입": "심오",
        "제목": "명예와의 결별",
        "본문": "오늘,\n당신은 명예와 결별해요.\n정관을 포기하고,\n세상의 인정을 구하지 않아요.\n쿨하게 돌아서요.\n이제 당신은,\n오직 자신을 위해 살 거예요.\n오늘은 타인의 시선에서 벗어나,\n진정한 자아를 찾는 날이에요.",
        "액션": "자신을 위해 사세요. 남들의 평가가 아니라, 당신 자신의 행복을 위해 선택하세요."
      },
      {
        "v": 4,
        "타입": "심오",
        "제목": "백마의 고삐를 풀다",
        "본문": "오늘,\n백마는 고삐를 풀어요.\n더 이상 누구도,\n당신을 통제할 수 없어요.\n완전한 자유예요.\n어디로 갈지,\n무엇을 할지는 오직 당신이 결정해요.\n오늘은 모든 구속에서 벗어나,\n진정한 자유를 누리는 날이에요.",
        "액션": "자유를 누리세요. 누구의 통제도 받지 말고, 당신이 원하는 대로 살아가세요."
      },
      {
        "v": 5,
        "타입": "심오",
        "제목": "정의의 포기",
        "본문": "오늘,\n당신은 정의를 포기해요.\n더 이상 옳고 그름을,\n따지지 않아요.\n세상은 복잡해요.\n흑백논리로 나눌 수 없어요.\n이제는 그냥,\n흐름에 몸을 맡겨요.\n오늘은 정의의 무게를 내려놓고,\n가볍게 사는 날이에요.",
        "액션": "가볍게 사세요. 모든 것을 판단하려 하지 말고, 있는 그대로 받아들이며 살아가세요."
      },
      {
        "v": 6,
        "타입": "중립",
        "제목": "모든 것과의 이별",
        "본문": "오늘,\n모든 것과 이별해요.\n익숙했던 것들,\n소중했던 것들.\n다 놓아줘야 해요.\n슬프지만,\n이것이 새로운 시작을 위한 과정이에요.\n오늘은 과거와 작별하고,\n미래를 맞이하는 날이에요.",
        "액션": "작별하세요. 슬프더라도 과거를 놓아주면, 새로운 것을 받아들일 준비가 될 거예요."
      },
      {
        "v": 7,
        "타입": "중립",
        "제목": "관계의 단절",
        "본문": "오늘,\n중요한 관계가 끊어질 수 있어요.\n친구든,\n연인이든,\n가족이든.\n이별의 순간이 올 수 있어요.\n슬프지만,\n때로는 이별도 필요해요.\n오늘은 끝난 관계를 정리하고,\n새로운 인연을 기다리는 날이에요.",
        "액션": "정리하세요. 끝난 관계에 매달리지 말고, 새로운 인연을 위한 마음의 공간을 만드세요."
      },
      {
        "v": 8,
        "타입": "중립",
        "제목": "고립의 순간",
        "본문": "오늘,\n당신은 혼자예요.\n주변에 아무도 없는 것 같아요.\n외롭고 쓸쓸해요.\n하지만 이 고립이,\n당신을 더 강하게 만들어요.\n오늘은 혼자만의 시간을 통해,\n자신을 더 깊이 이해하는 날이에요.",
        "액션": "혼자를 즐기세요. 고립이 두렵지만, 그 안에서 당신은 진정한 자신을 발견할 거예요."
      },
      {
        "v": 9,
        "타입": "중립",
        "제목": "새로운 출발 전야",
        "본문": "오늘,\n모든 것이 끝난 것 같아요.\n하지만 사실은,\n새로운 출발 직전이에요.\n끊어진 자리에,\n새로운 것이 들어올 거예요.\n희망을 가지세요.\n오늘은 끝과 시작 사이에서,\n새로운 미래를 준비하는 날이에요.",
        "액션": "희망을 가지세요. 지금은 끝처럼 보이지만, 곧 새로운 시작이 찾아올 거예요."
      },
      {
        "v": 10,
        "타입": "중립",
        "제목": "완전한 리셋",
        "본문": "오늘,\n모든 것을 리셋해요.\n과거는 지우고,\n현재에 집중하고,\n미래를 새롭게 그려요.\n완전히 새로운 시작이에요.\n두렵지만 설레기도 해요.\n오늘은 모든 것을 초기화하고,\n새로운 인생을 시작하는 날이에요.",
        "액션": "새롭게 시작하세요. 과거의 무게를 벗어던지고, 완전히 새로운 당신으로 살아가세요."
      }
    ],
    "태": [
      {
        "v": 1,
        "타입": "심오",
        "제목": "쇠의 잉태",
        "본문": "오늘,\n새로운 쇠가 잉태돼요.\n庚금이 午화 속에서,\n다시 생명을 얻어요.\n아직 형체는 없지만,\n가능성이 무궁무진해요.\n오늘은 새로운 꿈을,\n품기 시작하는 날이에요.",
        "액션": "꿈을 품으세요. 아직 구체적이지 않아도 괜찮아요. 마음속에 씨앗을 심으면 언젠가 싹을 틔울 거예요."
      },
      {
        "v": 2,
        "타입": "심오",
        "제목": "새로운 명예의 씨앗",
        "본문": "오늘,\n당신 안에 새로운 명예가 싹터요.\n정관이 다시 태어나요.\n아직 작고 미약하지만,\n분명히 존재해요.\n이것을 소중히 키우세요.\n오늘은 미래의 명예를,\n준비하기 시작하는 날이에요.",
        "액션": "준비하세요. 작은 씨앗이지만 소중히 돌보면, 언젠가 큰 나무로 자랄 거예요."
      },
      {
        "v": 3,
        "타입": "심오",
        "제목": "투명함의 재탄생",
        "본문": "오늘,\n당신의 솔직함이 다시 태어나요.\n나체도화의 기운이,\n새롭게 싹트기 시작해요.\n더 투명하고,\n더 진솔해질 거예요.\n오늘은 진심을 말하는 용기를,\n다시 얻는 날이에요.",
        "액션": "진심을 회복하세요. 다시 솔직해지는 용기를 내면, 사람들이 당신의 진정성을 알아볼 거예요."
      },
      {
        "v": 4,
        "타입": "심오",
        "제목": "백마의 태동",
        "본문": "오늘,\n새로운 백마가 태동해요.\n어미의 뱃속에서,\n생명이 움직이기 시작해요.\n아직 세상에 나오지 않았지만,\n곧 태어날 거예요.\n오늘은 새로운 가능성이,\n꿈틀대는 날이에요.",
        "액션": "가능성을 느껴보세요. 아직 보이지 않아도, 당신 안에 새로운 무언가가 자라고 있어요."
      },
      {
        "v": 5,
        "타입": "심오",
        "제목": "정의의 씨앗",
        "본문": "오늘,\n정의의 씨앗이 심겨요.\n아직 작고 약하지만,\n분명히 존재해요.\n이 씨앗을 잘 가꾸세요.\n오늘은 다시 정의를 믿고,\n옳은 길을 걷기 시작하는 날이에요.",
        "액션": "믿음을 회복하세요. 작은 정의의 씨앗을 소중히 키우면, 언젠가 세상을 바꿀 큰 나무가 될 거예요."
      },
      {
        "v": 6,
        "타입": "중립",
        "제목": "새로운 시작의 예감",
        "본문": "오늘,\n뭔가 새로운 것이 시작될 것 같아요.\n아직 명확하지 않지만,\n분명한 예감이 들어요.\n막연하지만,\n설레요.\n오늘은 새로운 가능성을,\n느끼는 날이에요.",
        "액션": "예감을 믿으세요. 아직 보이지 않아도, 당신의 직관이 말하는 것에 귀 기울이세요."
      },
      {
        "v": 7,
        "타입": "중립",
        "제목": "잉태된 꿈",
        "본문": "오늘,\n새로운 꿈이 잉태돼요.\n아직 구체적이지 않지만,\n마음속에 뭔가 싹터요.\n이 꿈을 소중히 품으세요.\n천천히 키우다 보면,\n언젠가 현실이 될 거예요.\n오늘은 미래를 상상하며,\n꿈을 품는 날이에요.",
        "액션": "꿈을 품으세요. 작고 막연해도 괜찮아요. 꿈을 포기하지 않으면 언젠가 이룰 수 있어요."
      },
      {
        "v": 8,
        "타입": "중립",
        "제목": "희미한 가능성",
        "본문": "오늘,\n희미하지만 가능성이 보여요.\n아직 확실하지 않아요.\n하지만 분명히 뭔가 있어요.\n이것을 놓치지 마세요.\n조심스럽게 다가가,\n가능성을 현실로 만드세요.\n오늘은 작은 기회를,\n발견하는 날이에요.",
        "액션": "기회를 잡으세요. 희미해 보여도, 조심스럽게 다가가면 큰 가능성이 될 수 있어요."
      },
      {
        "v": 9,
        "타입": "중립",
        "제목": "준비되는 미래",
        "본문": "오늘,\n미래가 준비되고 있어요.\n당신이 모르는 사이에,\n뭔가 자라고 있어요.\n아직 때가 아니라,\n보이지 않을 뿐이에요.\n조금만 더 기다리세요.\n오늘은 보이지 않는 곳에서,\n미래가 만들어지는 날이에요.",
        "액션": "인내하세요. 지금은 보이지 않지만, 때가 되면 준비된 미래가 모습을 드러낼 거예요."
      },
      {
        "v": 10,
        "타입": "중립",
        "제목": "생명의 움직임",
        "본문": "오늘,\n당신 안에서 뭔가 움직여요.\n작은 생명이,\n꿈틀대는 것 같아요.\n아직 형체는 없지만,\n분명히 느껴져요.\n이 움직임을 소중히 여기세요.\n오늘은 내면에서,\n새로운 것이 태동하는 날이에요.",
        "액션": "내면을 느껴보세요. 당신 안에서 무언가 자라고 있어요. 그것을 소중히 키우세요."
      }
    ],
    "양": [
      {
        "v": 1,
        "타입": "심오",
        "제목": "쇠를 키우는 시간",
        "본문": "오늘,\n어린 쇠가 양육돼요.\n庚금이 午화의 품에서,\n조금씩 자라요.\n아직 약하지만,\n매일 단단해지고 있어요.\n오늘은 자신을 돌보며,\n성장하는 날이에요.",
        "액션": "자신을 돌보세요. 매일 조금씩 자신에게 투자하면, 어느새 강하고 단단한 사람이 될 거예요."
      },
      {
        "v": 2,
        "타입": "심오",
        "제목": "명예를 키우다",
        "본문": "오늘,\n당신은 명예를 키워요.\n정관의 기운을,\n조금씩 쌓아가요.\n작은 성실함이,\n큰 신뢰로 자라요.\n오늘은 조금씩 쌓는,\n작은 노력의 날이에요.",
        "액션": "성실하게 쌓으세요. 작은 신뢰를 하나씩 쌓다 보면, 언젠가 큰 명예로 돌아올 거예요."
      },
      {
        "v": 3,
        "타입": "심오",
        "제목": "솔직함을 기르다",
        "본문": "오늘,\n당신의 솔직함이 자라요.\n나체도화의 투명함을,\n더 키워가요.\n진심을 말하는 연습,\n거짓 없이 사는 연습.\n오늘은 진정성을 키우는,\n소중한 날이에요.",
        "액션": "진심을 키우세요. 매일 조금씩 더 솔직해지면, 사람들이 당신을 더 신뢰하게 될 거예요."
      },
      {
        "v": 4,
        "타입": "심오",
        "제목": "백마를 훈련시키다",
        "본문": "오늘,\n어린 백마가 훈련받아요.\n달리는 법을,\n뛰어넘는 법을 배워요.\n아직 서툴지만,\n매일 나아지고 있어요.\n오늘은 자신을 단련하며,\n성장하는 날이에요.",
        "액션": "훈련하세요. 매일 조금씩 자신을 단련하면, 언젠가 세상을 달릴 준비가 될 거예요."
      },
      {
        "v": 5,
        "타입": "심오",
        "제목": "정의를 배우다",
        "본문": "오늘,\n당신은 정의를 배워요.\n옳고 그름을 구분하는 법,\n약자를 보호하는 법.\n하나씩 배워가요.\n오늘은 세상의 이치를 깨우치며,\n정의로운 사람으로 자라는 날이에요.",
        "액션": "배우세요. 세상의 이치를 하나씩 깨우치면, 정의로운 리더로 성장할 거예요."
      },
      {
        "v": 6,
        "타입": "중립",
        "제목": "성장의 기쁨",
        "본문": "오늘,\n당신은 조금씩 자라요.\n어제보다 오늘,\n오늘보다 내일.\n눈에 띄지 않는 작은 성장이지만,\n분명히 나아지고 있어요.\n오늘은 자신의 성장을,\n느끼는 날이에요.",
        "액션": "성장을 느끼세요. 작은 변화라도 자신을 칭찬하고, 계속 앞으로 나아가세요."
      },
      {
        "v": 7,
        "타입": "중립",
        "제목": "보살핌을 받다",
        "본문": "오늘,\n누군가가 당신을 돌봐줘요.\n따뜻한 손길이,\n당신을 보살펴요.\n그 사랑을 받아들이세요.\n혼자가 아니에요.\n오늘은 다른 사람의 도움을 받으며,\n함께 성장하는 날이에요.",
        "액션": "도움을 받으세요. 혼자 모든 것을 하려 하지 말고, 주변의 사랑과 도움을 받아들이세요."
      },
      {
        "v": 8,
        "타입": "중립",
        "제목": "조금씩 나아지다",
        "본문": "오늘,\n당신은 조금씩 나아져요.\n완벽하지 않지만,\n어제보다는 나아요.\n이 작은 진전을,\n소중히 여기세요.\n오늘은 작은 성장을 기뻐하며,\n스스로를 격려하는 날이에요.",
        "액션": "스스로를 격려하세요. 완벽하지 않아도 괜찮아요. 조금씩 나아지는 것만으로도 충분해요."
      },
      {
        "v": 9,
        "타입": "중립",
        "제목": "미래를 준비하다",
        "본문": "오늘,\n당신은 미래를 준비해요.\n지금 배우는 것들이,\n나중에 큰 자산이 될 거예요.\n당장 결과가 보이지 않아도,\n꾸준히 노력하세요.\n오늘은 미래를 위한,\n투자의 날이에요.",
        "액션": "투자하세요. 지금의 노력이 미래의 당신을 만들어요. 꾸준히 배우고 성장하세요."
      },
      {
        "v": 10,
        "타입": "중립",
        "제목": "사랑으로 자라다",
        "본문": "오늘,\n당신은 사랑 속에서 자라요.\n주변 사람들의 관심과 애정이,\n당신을 든든하게 만들어요.\n이 사랑에 감사하세요.\n오늘은 사랑을 받으며,\n따뜻한 사람으로 성장하는 날이에요.",
        "액션": "감사하세요. 주변의 사랑에 감사하고, 그 사랑을 다른 사람에게도 나눠주세요."
      }
    ]
  }
}